pylammpstrj.cpython-310-x86_64-linux-gnu.so
pylammpstrj/pylammpstrjmodule.c
pylammpstrj/include/pylammpstrjmodule.h
pylammpstrj/include/utils.h
pylammpstrj/lammpstrj/read.c
pylammpstrj/lammpstrj/box.c
pylammpstrj/lammpstrj/atom.c
pylammpstrj/lammpstrj/skip.c
pylammpstrj/lammpstrj/select.c
pylammpstrj/lammpstrj/trajectory.c
pylammpstrj/lammpstrj/average.c
pylammpstrj-1.0.2.dist-info/RECORD
pylammpstrj-1.0.2.dist-info/top_level.txt
pylammpstrj-1.0.2.dist-info/WHEEL
pylammpstrj-1.0.2.dist-info/LICENSE
pylammpstrj-1.0.2.dist-info/METADATA
