Metadata-Version: 2.1
Name: pylammpstrj
Version: 1.0.2
Summary: Processing LAMMPS trajectory files.
Author-email: Heiarii Lou Chao <heiariilouchao@gmail.com>
License: GNU GENERAL PUBLIC LICENSE
Project-URL: Repository, https://github.com/heiariilouchao/thesis
Keywords: lammps,trajectory,processing
Classifier: Development Status :: 4 - Beta
Classifier: Programming Language :: C
Classifier: Programming Language :: Python :: 3.8
Classifier: Intended Audience :: Science/Research
Classifier: Topic :: Scientific/Engineering :: Physics
Classifier: Topic :: Utilities
Requires-Python: >=3.8
License-File: LICENSE
